pytest_atf_allure/__init__.py
pytest_atf_allure/helper.py
pytest_atf_allure/listener.py
pytest_atf_allure/plugin.py
pytest_atf_allure/utils.py
pytest_atf_allure-2023.11.29.dist-info/entry_points.txt
pytest_atf_allure-2023.11.29.dist-info/METADATA
pytest_atf_allure-2023.11.29.dist-info/WHEEL
pytest_atf_allure-2023.11.29.dist-info/RECORD
