Metadata-Version: 2.1
Name: pytest-atf-allure
Version: 2023.11.29
Summary: 基于allure-pytest进行自定义
Author: mf.liang
Author-email: mf.liang@outlook.com
Requires-Python: >=3.9,<4.0
Classifier: Programming Language :: Python :: 3
Classifier: Programming Language :: Python :: 3.9
Classifier: Programming Language :: Python :: 3.10
Classifier: Programming Language :: Python :: 3.11
Requires-Dist: allure-python-commons (>=2.13.2,<3.0.0)
Requires-Dist: pytest (>=7.4.2,<8.0.0)
